etc_activelearning/__init__.py
etc_activelearning/_version.py
etc_activelearning-1.0.0.data/data/share/jupyter/labextensions/etc_activelearning/package.json
etc_activelearning-1.0.0.data/data/share/jupyter/labextensions/etc_activelearning/static/372.1f5a6c9e6133a924371c.js
etc_activelearning-1.0.0.data/data/share/jupyter/labextensions/etc_activelearning/static/747.cedc32c1f334463d9795.js
etc_activelearning-1.0.0.data/data/share/jupyter/labextensions/etc_activelearning/static/remoteEntry.7eeb0a1565b5bc4ff4e9.js
etc_activelearning-1.0.0.data/data/share/jupyter/labextensions/etc_activelearning/static/style.js
etc_activelearning-1.0.0.data/data/share/jupyter/labextensions/etc_activelearning/static/third-party-licenses.json
etc_activelearning-1.0.0.data/data/share/jupyter/labextensions/etc_activelearning/install.json
etc_activelearning-1.0.0.dist-info/METADATA
etc_activelearning-1.0.0.dist-info/WHEEL
etc_activelearning-1.0.0.dist-info/licenses/LICENSE
etc_activelearning-1.0.0.dist-info/RECORD
