Metadata-Version: 2.1
Name: etc_activelearning
Version: 1.0.0
Summary: A JupyterLab extension that enables data-science instructors to improve teaching by including tasks for students to complete during video lecutres on MOOCs
Project-URL: Homepage, https://github.com/bharathvariar/etc-activelearning.git
Project-URL: Bug Tracker, https://github.com/bharathvariar/etc-activelearning.git/issues
Project-URL: Repository, https://github.com/bharathvariar/etc-activelearning.git.git
Author-email: Bharath Variar <variarb@umich.edu>
License: BSD 3-Clause License
License-File: LICENSE
Classifier: Framework :: Jupyter
Classifier: Framework :: Jupyter :: JupyterLab
Classifier: Framework :: Jupyter :: JupyterLab :: 4
Classifier: Framework :: Jupyter :: JupyterLab :: Extensions
Classifier: Framework :: Jupyter :: JupyterLab :: Extensions :: Prebuilt
Classifier: License :: OSI Approved :: BSD License
Classifier: Programming Language :: Python
Classifier: Programming Language :: Python :: 3
Classifier: Programming Language :: Python :: 3.8
Classifier: Programming Language :: Python :: 3.9
Classifier: Programming Language :: Python :: 3.10
Classifier: Programming Language :: Python :: 3.11
Requires-Python: >=3.8
